odoo/addons/purchase_manual_currency/README.rst
odoo/addons/purchase_manual_currency/__init__.py
odoo/addons/purchase_manual_currency/__manifest__.py
odoo/addons/purchase_manual_currency/i18n/es.po
odoo/addons/purchase_manual_currency/i18n/it.po
odoo/addons/purchase_manual_currency/i18n/pt_BR.po
odoo/addons/purchase_manual_currency/i18n/purchase_manual_currency.pot
odoo/addons/purchase_manual_currency/models/__init__.py
odoo/addons/purchase_manual_currency/models/purchase.py
odoo/addons/purchase_manual_currency/models/purchase_order_line.py
odoo/addons/purchase_manual_currency/models/res_company.py
odoo/addons/purchase_manual_currency/models/res_config_settings.py
odoo/addons/purchase_manual_currency/readme/CONTRIBUTORS.md
odoo/addons/purchase_manual_currency/readme/DESCRIPTION.md
odoo/addons/purchase_manual_currency/readme/USAGE.md
odoo/addons/purchase_manual_currency/static/description/icon.png
odoo/addons/purchase_manual_currency/static/description/index.html
odoo/addons/purchase_manual_currency/tests/__init__.py
odoo/addons/purchase_manual_currency/tests/test_purchase_manual_currency.py
odoo/addons/purchase_manual_currency/views/purchase_views.xml
odoo/addons/purchase_manual_currency/views/res_config_settings_views.xml
odoo_addon_purchase_manual_currency-18.0.1.0.0.5.dist-info/METADATA
odoo_addon_purchase_manual_currency-18.0.1.0.0.5.dist-info/WHEEL
odoo_addon_purchase_manual_currency-18.0.1.0.0.5.dist-info/top_level.txt
odoo_addon_purchase_manual_currency-18.0.1.0.0.5.dist-info/RECORD
